{"metadata": {"dbt_schema_version": "https://schemas.getdbt.com/dbt/run-results/v4.json", "dbt_version": "1.0.1", "generated_at": "2022-01-14T04:02:04.726687Z", "invocation_id": "830099a8-5206-46af-850f-3ca60ddc0f0e", "env": {}}, "results": [{"status": "success", "timing": [{"name": "compile", "started_at": "2022-01-14T04:02:03.909553Z", "completed_at": "2022-01-14T04:02:03.920451Z"}, {"name": "execute", "started_at": "2022-01-14T04:02:03.922189Z", "completed_at": "2022-01-14T04:02:03.922368Z"}], "thread_id": "Thread-1", "execution_time": 0.017385244369506836, "adapter_response": {}, "message": null, "failures": null, "unique_id": "seed.jaffle_shop.raw_customers"}, {"status": "success", "timing": [{"name": "compile", "started_at": "2022-01-14T04:02:03.930305Z", "completed_at": "2022-01-14T04:02:03.938270Z"}, {"name": "execute", "started_at": "2022-01-14T04:02:03.939649Z", "completed_at": "2022-01-14T04:02:03.939731Z"}], "thread_id": "Thread-1", "execution_time": 0.013287067413330078, "adapter_response": {}, "message": null, "failures": null, "unique_id": "seed.jaffle_shop.raw_orders"}, {"status": "success", "timing": [{"name": "compile", "started_at": "2022-01-14T04:02:03.946270Z", "completed_at": "2022-01-14T04:02:03.952170Z"}, {"name": "execute", "started_at": "2022-01-14T04:02:03.953781Z", "completed_at": "2022-01-14T04:02:03.953843Z"}], "thread_id": "Thread-1", "execution_time": 0.011828422546386719, "adapter_response": {}, "message": null, "failures": null, "unique_id": "seed.jaffle_shop.raw_payments"}, {"status": "success", "timing": [{"name": "compile", "started_at": "2022-01-14T04:02:03.961717Z", "completed_at": "2022-01-14T04:02:03.982741Z"}, {"name": "execute", "started_at": "2022-01-14T04:02:03.985529Z", "completed_at": "2022-01-14T04:02:03.985585Z"}], "thread_id": "Thread-1", "execution_time": 0.028484106063842773, "adapter_response": {}, "message": null, "failures": null, "unique_id": "model.jaffle_shop.stg_customers"}, {"status": "success", "timing": [{"name": "compile", "started_at": "2022-01-14T04:02:03.993986Z", "completed_at": "2022-01-14T04:02:04.014322Z"}, {"name": "execute", "started_at": "2022-01-14T04:02:04.017349Z", "completed_at": "2022-01-14T04:02:04.017406Z"}], "thread_id": "Thread-1", "execution_time": 0.029587507247924805, "adapter_response": {}, "message": null, "failures": null, "unique_id": "model.jaffle_shop.stg_orders"}, {"status": "success", "timing": [{"name": "compile", "started_at": "2022-01-14T04:02:04.027637Z", "completed_at": "2022-01-14T04:02:04.046210Z"}, {"name": "execute", "started_at": "2022-01-14T04:02:04.047980Z", "completed_at": "2022-01-14T04:02:04.048027Z"}], "thread_id": "Thread-1", "execution_time": 0.026120424270629883, "adapter_response": {}, "message": null, "failures": null, "unique_id": "model.jaffle_shop.stg_payments"}, {"status": "success", "timing": [{"name": "compile", "started_at": "2022-01-14T04:02:04.055284Z", "completed_at": "2022-01-14T04:02:04.144532Z"}, {"name": "execute", "started_at": "2022-01-14T04:02:04.146438Z", "completed_at": "2022-01-14T04:02:04.146485Z"}], "thread_id": "Thread-1", "execution_time": 0.09516334533691406, "adapter_response": {}, "message": null, "failures": null, "unique_id": "model.jaffle_shop.stg_payments_jinja"}, {"status": "success", "timing": [{"name": "compile", "started_at": "2022-01-14T04:02:04.152862Z", "completed_at": "2022-01-14T04:02:04.209106Z"}, {"name": "execute", "started_at": "2022-01-14T04:02:04.210843Z", "completed_at": "2022-01-14T04:02:04.210888Z"}], "thread_id": "Thread-1", "execution_time": 0.061974525451660156, "adapter_response": {}, "message": null, "failures": null, "unique_id": "test.jaffle_shop.not_null_stg_customers_customer_id.e2cfb1f9aa"}, {"status": "success", "timing": [{"name": "compile", "started_at": "2022-01-14T04:02:04.217339Z", "completed_at": "2022-01-14T04:02:04.255654Z"}, {"name": "execute", "started_at": "2022-01-14T04:02:04.257631Z", "completed_at": "2022-01-14T04:02:04.257679Z"}], "thread_id": "Thread-1", "execution_time": 0.044591426849365234, "adapter_response": {}, "message": null, "failures": null, "unique_id": "test.jaffle_shop.unique_stg_customers_customer_id.c7614daada"}, {"status": "success", "timing": [{"name": "compile", "started_at": "2022-01-14T04:02:04.263700Z", "completed_at": "2022-01-14T04:02:04.319953Z"}, {"name": "execute", "started_at": "2022-01-14T04:02:04.321808Z", "completed_at": "2022-01-14T04:02:04.321873Z"}], "thread_id": "Thread-1", "execution_time": 0.0622859001159668, "adapter_response": {}, "message": null, "failures": null, "unique_id": "test.jaffle_shop.accepted_values_stg_orders_status__placed__shipped__completed__return_pending__returned.080fb20aad"}, {"status": "success", "timing": [{"name": "compile", "started_at": "2022-01-14T04:02:04.329815Z", "completed_at": "2022-01-14T04:02:04.366165Z"}, {"name": "execute", "started_at": "2022-01-14T04:02:04.368478Z", "completed_at": "2022-01-14T04:02:04.368534Z"}], "thread_id": "Thread-1", "execution_time": 0.04283261299133301, "adapter_response": {}, "message": null, "failures": null, "unique_id": "test.jaffle_shop.not_null_stg_orders_order_id.81cfe2fe64"}, {"status": "success", "timing": [{"name": "compile", "started_at": "2022-01-14T04:02:04.375004Z", "completed_at": "2022-01-14T04:02:04.396061Z"}, {"name": "execute", "started_at": "2022-01-14T04:02:04.398578Z", "completed_at": "2022-01-14T04:02:04.398645Z"}], "thread_id": "Thread-1", "execution_time": 0.027940034866333008, "adapter_response": {}, "message": null, "failures": null, "unique_id": "test.jaffle_shop.unique_stg_orders_order_id.e3b841c71a"}, {"status": "success", "timing": [{"name": "compile", "started_at": "2022-01-14T04:02:04.406836Z", "completed_at": "2022-01-14T04:02:04.429352Z"}, {"name": "execute", "started_at": "2022-01-14T04:02:04.431115Z", "completed_at": "2022-01-14T04:02:04.431156Z"}], "thread_id": "Thread-1", "execution_time": 0.02803492546081543, "adapter_response": {}, "message": null, "failures": null, "unique_id": "model.jaffle_shop.customers"}, {"status": "success", "timing": [{"name": "compile", "started_at": "2022-01-14T04:02:04.435770Z", "completed_at": "2022-01-14T04:02:04.448287Z"}, {"name": "execute", "started_at": "2022-01-14T04:02:04.449302Z", "completed_at": "2022-01-14T04:02:04.449331Z"}], "thread_id": "Thread-1", "execution_time": 0.016146183013916016, "adapter_response": {}, "message": null, "failures": null, "unique_id": "model.jaffle_shop.orders"}, {"status": "success", "timing": [{"name": "compile", "started_at": "2022-01-14T04:02:04.453838Z", "completed_at": "2022-01-14T04:02:04.467238Z"}, {"name": "execute", "started_at": "2022-01-14T04:02:04.468015Z", "completed_at": "2022-01-14T04:02:04.468035Z"}], "thread_id": "Thread-1", "execution_time": 0.016126394271850586, "adapter_response": {}, "message": null, "failures": null, "unique_id": "test.jaffle_shop.accepted_values_stg_payments_payment_method__credit_card__coupon__bank_transfer__gift_card.3c3820f278"}, {"status": "success", "timing": [{"name": "compile", "started_at": "2022-01-14T04:02:04.470582Z", "completed_at": "2022-01-14T04:02:04.480117Z"}, {"name": "execute", "started_at": "2022-01-14T04:02:04.480978Z", "completed_at": "2022-01-14T04:02:04.481003Z"}], "thread_id": "Thread-1", "execution_time": 0.012122154235839844, "adapter_response": {}, "message": null, "failures": null, "unique_id": "test.jaffle_shop.not_null_stg_payments_payment_id.c19cc50075"}, {"status": "success", "timing": [{"name": "compile", "started_at": "2022-01-14T04:02:04.483957Z", "completed_at": "2022-01-14T04:02:04.494094Z"}, {"name": "execute", "started_at": "2022-01-14T04:02:04.495054Z", "completed_at": "2022-01-14T04:02:04.495080Z"}], "thread_id": "Thread-1", "execution_time": 0.012935400009155273, "adapter_response": {}, "message": null, "failures": null, "unique_id": "test.jaffle_shop.unique_stg_payments_payment_id.3744510712"}, {"status": "success", "timing": [{"name": "compile", "started_at": "2022-01-14T04:02:04.498428Z", "completed_at": "2022-01-14T04:02:04.509542Z"}, {"name": "execute", "started_at": "2022-01-14T04:02:04.510466Z", "completed_at": "2022-01-14T04:02:04.510491Z"}], "thread_id": "Thread-1", "execution_time": 0.014230728149414062, "adapter_response": {}, "message": null, "failures": null, "unique_id": "test.jaffle_shop.not_null_customers_customer_id.5c9bf9911d"}, {"status": "success", "timing": [{"name": "compile", "started_at": "2022-01-14T04:02:04.513584Z", "completed_at": "2022-01-14T04:02:04.527954Z"}, {"name": "execute", "started_at": "2022-01-14T04:02:04.529217Z", "completed_at": "2022-01-14T04:02:04.529251Z"}], "thread_id": "Thread-1", "execution_time": 0.01775503158569336, "adapter_response": {}, "message": null, "failures": null, "unique_id": "test.jaffle_shop.unique_customers_customer_id.c5af1ff4b1"}, {"status": "success", "timing": [{"name": "compile", "started_at": "2022-01-14T04:02:04.532858Z", "completed_at": "2022-01-14T04:02:04.549921Z"}, {"name": "execute", "started_at": "2022-01-14T04:02:04.550930Z", "completed_at": "2022-01-14T04:02:04.550956Z"}], "thread_id": "Thread-1", "execution_time": 0.01992201805114746, "adapter_response": {}, "message": null, "failures": null, "unique_id": "test.jaffle_shop.accepted_values_orders_status__placed__shipped__completed__return_pending__returned.be6b5b5ec3"}, {"status": "success", "timing": [{"name": "compile", "started_at": "2022-01-14T04:02:04.554097Z", "completed_at": "2022-01-14T04:02:04.565762Z"}, {"name": "execute", "started_at": "2022-01-14T04:02:04.567143Z", "completed_at": "2022-01-14T04:02:04.567178Z"}], "thread_id": "Thread-1", "execution_time": 0.015321731567382812, "adapter_response": {}, "message": null, "failures": null, "unique_id": "test.jaffle_shop.not_null_orders_amount.106140f9fd"}, {"status": "success", "timing": [{"name": "compile", "started_at": "2022-01-14T04:02:04.570995Z", "completed_at": "2022-01-14T04:02:04.582201Z"}, {"name": "execute", "started_at": "2022-01-14T04:02:04.583243Z", "completed_at": "2022-01-14T04:02:04.583270Z"}], "thread_id": "Thread-1", "execution_time": 0.014311075210571289, "adapter_response": {}, "message": null, "failures": null, "unique_id": "test.jaffle_shop.not_null_orders_bank_transfer_amount.7743500c49"}, {"status": "success", "timing": [{"name": "compile", "started_at": "2022-01-14T04:02:04.586354Z", "completed_at": "2022-01-14T04:02:04.597483Z"}, {"name": "execute", "started_at": "2022-01-14T04:02:04.598515Z", "completed_at": "2022-01-14T04:02:04.598540Z"}], "thread_id": "Thread-1", "execution_time": 0.014044046401977539, "adapter_response": {}, "message": null, "failures": null, "unique_id": "test.jaffle_shop.not_null_orders_coupon_amount.ab90c90625"}, {"status": "success", "timing": [{"name": "compile", "started_at": "2022-01-14T04:02:04.601607Z", "completed_at": "2022-01-14T04:02:04.615297Z"}, {"name": "execute", "started_at": "2022-01-14T04:02:04.616293Z", "completed_at": "2022-01-14T04:02:04.616326Z"}], "thread_id": "Thread-1", "execution_time": 0.016669511795043945, "adapter_response": {}, "message": null, "failures": null, "unique_id": "test.jaffle_shop.not_null_orders_credit_card_amount.d3ca593b59"}, {"status": "success", "timing": [{"name": "compile", "started_at": "2022-01-14T04:02:04.619460Z", "completed_at": "2022-01-14T04:02:04.630866Z"}, {"name": "execute", "started_at": "2022-01-14T04:02:04.632229Z", "completed_at": "2022-01-14T04:02:04.632256Z"}], "thread_id": "Thread-1", "execution_time": 0.014586925506591797, "adapter_response": {}, "message": null, "failures": null, "unique_id": "test.jaffle_shop.not_null_orders_customer_id.c5f02694af"}, {"status": "success", "timing": [{"name": "compile", "started_at": "2022-01-14T04:02:04.636366Z", "completed_at": "2022-01-14T04:02:04.648121Z"}, {"name": "execute", "started_at": "2022-01-14T04:02:04.650041Z", "completed_at": "2022-01-14T04:02:04.650075Z"}], "thread_id": "Thread-1", "execution_time": 0.01669144630432129, "adapter_response": {}, "message": null, "failures": null, "unique_id": "test.jaffle_shop.not_null_orders_gift_card_amount.413a0d2d7a"}, {"status": "success", "timing": [{"name": "compile", "started_at": "2022-01-14T04:02:04.654107Z", "completed_at": "2022-01-14T04:02:04.669456Z"}, {"name": "execute", "started_at": "2022-01-14T04:02:04.671334Z", "completed_at": "2022-01-14T04:02:04.671378Z"}], "thread_id": "Thread-1", "execution_time": 0.019761085510253906, "adapter_response": {}, "message": null, "failures": null, "unique_id": "test.jaffle_shop.not_null_orders_order_id.cf6c17daed"}, {"status": "success", "timing": [{"name": "compile", "started_at": "2022-01-14T04:02:04.675460Z", "completed_at": "2022-01-14T04:02:04.701819Z"}, {"name": "execute", "started_at": "2022-01-14T04:02:04.703129Z", "completed_at": "2022-01-14T04:02:04.703163Z"}], "thread_id": "Thread-1", "execution_time": 0.030460596084594727, "adapter_response": {}, "message": null, "failures": null, "unique_id": "test.jaffle_shop.relationships_orders_customer_id__customer_id__ref_customers_.c6ec7f58f2"}, {"status": "success", "timing": [{"name": "compile", "started_at": "2022-01-14T04:02:04.706729Z", "completed_at": "2022-01-14T04:02:04.718372Z"}, {"name": "execute", "started_at": "2022-01-14T04:02:04.719373Z", "completed_at": "2022-01-14T04:02:04.719401Z"}], "thread_id": "Thread-1", "execution_time": 0.014491796493530273, "adapter_response": {}, "message": null, "failures": null, "unique_id": "test.jaffle_shop.unique_orders_order_id.fed79b3a6e"}], "elapsed_time": 3.787017822265625, "args": {"write_json": true, "use_colors": true, "printer_width": 80, "version_check": true, "partial_parse": true, "static_parser": true, "profiles_dir": "/home/tan/.dbt", "send_anonymous_usage_stats": true, "event_buffer_size": 100000, "compile": true, "which": "generate", "rpc_method": "docs.generate", "indirect_selection": "eager"}}